spring_pkg/__init__.py
spring_pkg/spring_api.md
spring_pkg/actuator/__init__.py
spring_pkg/actuator/root.py
spring_pkg/coding/__init__.py
spring_pkg/coding/deprecated.py
spring_pkg/coding/locked_status.py
spring_pkg/database/__init__.py
spring_pkg/database/base/__init__.py
spring_pkg/database/base/conn.py
spring_pkg/database/base/database.py
spring_pkg/database/base/database_root.py
spring_pkg/database/base/db_entity.py
spring_pkg/database/base/db_entity_base.py
spring_pkg/database/base/dbdec.py
spring_pkg/database/base/dbfield.py
spring_pkg/database/base/dbtable.py
spring_pkg/database/base/query_expression.py
spring_pkg/database/base/query_result.py
spring_pkg/database/memory/__init__.py
spring_pkg/database/memory/db.py
spring_pkg/database/postgres/__init__.py
spring_pkg/database/postgres/config.py
spring_pkg/database/postgres/conn_pool.py
spring_pkg/database/postgres/connection.py
spring_pkg/database/postgres/main_api.py
spring_pkg/database/postgres/postgres_db.py
spring_pkg/database/postgres/service.py
spring_pkg/database/postgres/sql.py
spring_pkg/monitor/__init__.py
spring_pkg/monitor/memory_watch.py
spring_pkg/monitor/thread_db.py
spring_pkg/monitor/client/__init__.py
spring_pkg/monitor/client/livedata.py
spring_pkg/monitor/client/main_api.py
spring_pkg/monitor/client/methods.py
spring_pkg/monitor/client/pagelogs.py
spring_pkg/monitor/client/pip_pkgs.py
spring_pkg/monitor/client/pod_hub_sync.py
spring_pkg/monitor/client/time_watch.py
spring_pkg/monitor/server/__init__.py
spring_pkg/monitor/server/app_package.py
spring_pkg/monitor/server/app_package_changes.py
spring_pkg/monitor/server/pod_hub_ctrl.py
spring_pkg/monitor/server/pod_hub_data.py
spring_pkg/monitor/server/podhub_app.py
spring_pkg/monitor/server/podhub_data.py
spring_pkg/monitor/server/podhub_info.py
spring_pkg/notifications/__init__.py
spring_pkg/notifications/core.py
spring_pkg/notifications/notification_center.py
spring_pkg/notifications/notification_data.py
dcnr_spring-1.0.2.dist-info/METADATA
dcnr_spring-1.0.2.dist-info/WHEEL
dcnr_spring-1.0.2.dist-info/RECORD
