Metadata-Version: 2.4
Name: dcnr-spring
Version: 1.0.2
Summary: Scheduling python functions for execution.
Project-URL: Homepage, https://dcnr-utilities.com
Author-email: Peter Kollath <peter.kollath@gopal.home.sk>
License: MIT
Keywords: python,scheduler
Classifier: License :: OSI Approved :: MIT License
Classifier: Operating System :: OS Independent
Classifier: Programming Language :: Python :: 3
Requires-Python: >=3.9
